drjournal/__main__.py
drjournal/journal.py
drjournal-0.1.4.dist-info/METADATA
drjournal-0.1.4.dist-info/WHEEL
drjournal-0.1.4.dist-info/entry_points.txt
drjournal-0.1.4.dist-info/top_level.txt
drjournal-0.1.4.dist-info/RECORD
